LICENSE.txt
MANIFEST.in
README.rst
setup.py
Navigator.egg-info/PKG-INFO
Navigator.egg-info/SOURCES.txt
Navigator.egg-info/dependency_links.txt
Navigator.egg-info/pbr.json
Navigator.egg-info/requires.txt
Navigator.egg-info/top_level.txt
navigator/__init__.py
navigator/decorators.py
navigator/navigator.py
navigator/ui.py