Metadata-Version: 1.1
Name: Navigator
Version: 0.2.2
Summary: A framework to create simple, interactive command line tools.
Home-page: https://github.com/Andytom/navigator
Author: Thomas O'Donnell
Author-email: UNKNOWN
License: BSD 3-Clause License
Platform: UNKNOWN
Classifier: Development Status :: 3 - Alpha
Classifier: Environment :: Console
Classifier: Intended Audience :: Developers
Classifier: License :: OSI Approved :: BSD License
Classifier: Programming Language :: Python :: 2.7
Classifier: Programming Language :: Python :: 3.2
Classifier: Programming Language :: Python :: 3.3
Classifier: Programming Language :: Python :: 3.4
Classifier: Programming Language :: Python :: 3.5
